topsis_102103043/__init__.py
topsis_102103043/topsis_102103043.py
topsis_102103043-1.1.0.dist-info/LICENSE
topsis_102103043-1.1.0.dist-info/METADATA
topsis_102103043-1.1.0.dist-info/WHEEL
topsis_102103043-1.1.0.dist-info/entry_points.txt
topsis_102103043-1.1.0.dist-info/top_level.txt
topsis_102103043-1.1.0.dist-info/RECORD
