Metadata-Version: 2.1
Name: topsis_102103043
Version: 1.1.0
Summary: A Python package to rank ML models/choices using topsis technique
Home-page: https://github.com/iosaman503/topsis-package.git
Author: Aman Verma
Author-email: amanverma24680@gmail.com
License: MIT
Classifier: License :: OSI Approved :: MIT License
Classifier: Programming Language :: Python :: 3
Classifier: Programming Language :: Python :: 3.7
License-File: LICENSE
